verifyTelegram/WebApp.py
verifyTelegram/__init__.py
verifyTelegram-1.0.dist-info/LICENSE
verifyTelegram-1.0.dist-info/LICENSE.txt
verifyTelegram-1.0.dist-info/METADATA
verifyTelegram-1.0.dist-info/WHEEL
verifyTelegram-1.0.dist-info/top_level.txt
verifyTelegram-1.0.dist-info/RECORD
