Metadata-Version: 2.1
Name: verifyTelegram
Version: 1.0
Summary: This Python module securely validates and extracts user data from a URL-encoded string, using HMAC and SHA-256 for data integrity. It features a User class to structure user information and a Data class for validation and data parsing. Ideal for web applications needing secure user authentication and data management, it's easy to integrate and use.
Home-page: https://github.com/D34DBOY/verifyTelegram.git
Author: Mohammad Mohammadi Bijaneh
Author-email: hiostad6@gmail.com
Maintainer-email: Mohammad Mohammadi Bijaneh <hiostad6@gmail.com>
License: MIT License
Project-URL: Repository, https://github.com/D34DBOY/verifyTelegram.git
Requires-Python: >=3.8
License-File: LICENSE
License-File: LICENSE.txt
